[
  {
    "ContainingType": "sharp_01.Controllers.BooksController",
    "Method": "GetAll",
    "RelativePath": "api/Books",
    "HttpMethod": "GET",
    "IsController": true,
    "Order": 0,
    "Parameters": [],
    "ReturnTypes": []
  },
  {
    "ContainingType": "sharp_01.Controllers.CustomersController",
    "Method": "GetAll",
    "RelativePath": "api/Customers",
    "HttpMethod": "GET",
    "IsController": true,
    "Order": 0,
    "Parameters": [],
    "ReturnTypes": []
  },
  {
    "ContainingType": "sharp_01.Controllers.EmployeesController",
    "Method": "GetAll",
    "RelativePath": "api/Employees",
    "HttpMethod": "GET",
    "IsController": true,
    "Order": 0,
    "Parameters": [],
    "ReturnTypes": []
  },
  {
    "ContainingType": "sharp_01.Controllers.EmployeesController",
    "Method": "Create",
    "RelativePath": "api/Employees",
    "HttpMethod": "POST",
    "IsController": true,
    "Order": 0,
    "Parameters": [
      {
        "Name": "e",
        "Type": "sharp_01.Models.Employee",
        "IsRequired": true
      }
    ],
    "ReturnTypes": []
  },
  {
    "ContainingType": "sharp_01.Controllers.LoansController",
    "Method": "Create",
    "RelativePath": "api/Loans",
    "HttpMethod": "POST",
    "IsController": true,
    "Order": 0,
    "Parameters": [
      {
        "Name": "loan",
        "Type": "sharp_01.Models.Loan",
        "IsRequired": true
      }
    ],
    "ReturnTypes": []
  },
  {
    "ContainingType": "sharp_01.Controllers.OrdersController",
    "Method": "Create",
    "RelativePath": "api/Orders",
    "HttpMethod": "POST",
    "IsController": true,
    "Order": 0,
    "Parameters": [
      {
        "Name": "order",
        "Type": "sharp_01.Models.Order",
        "IsRequired": true
      }
    ],
    "ReturnTypes": []
  },
  {
    "ContainingType": "sharp_01.Controllers.ProductsController",
    "Method": "GetAll",
    "RelativePath": "api/Products",
    "HttpMethod": "GET",
    "IsController": true,
    "Order": 0,
    "Parameters": [],
    "ReturnTypes": []
  },
  {
    "ContainingType": "sharp_01.Controllers.ProductsController",
    "Method": "Create",
    "RelativePath": "api/Products",
    "HttpMethod": "POST",
    "IsController": true,
    "Order": 0,
    "Parameters": [
      {
        "Name": "product",
        "Type": "sharp_01.Models.Product",
        "IsRequired": true
      }
    ],
    "ReturnTypes": []
  },
  {
    "ContainingType": "sharp_01.Controllers.ReservationsController",
    "Method": "GetAll",
    "RelativePath": "api/Reservations",
    "HttpMethod": "GET",
    "IsController": true,
    "Order": 0,
    "Parameters": [],
    "ReturnTypes": []
  },
  {
    "ContainingType": "sharp_01.Controllers.ReservationsController",
    "Method": "Create",
    "RelativePath": "api/Reservations",
    "HttpMethod": "POST",
    "IsController": true,
    "Order": 0,
    "Parameters": [
      {
        "Name": "r",
        "Type": "sharp_01.Models.Reservation",
        "IsRequired": true
      }
    ],
    "ReturnTypes": []
  },
  {
    "ContainingType": "sharp_01.Controllers.StandController",
    "Method": "GetCar",
    "RelativePath": "api/Stand/GetCar",
    "HttpMethod": "GET",
    "IsController": true,
    "Order": 0,
    "Parameters": [
      {
        "Name": "CarID",
        "Type": "System.Int32",
        "IsRequired": false
      }
    ],
    "ReturnTypes": []
  },
  {
    "ContainingType": "sharp_01.Controllers.StudentsController",
    "Method": "GetAll",
    "RelativePath": "api/Students",
    "HttpMethod": "GET",
    "IsController": true,
    "Order": 0,
    "Parameters": [],
    "ReturnTypes": []
  },
  {
    "ContainingType": "sharp_01.Controllers.StudentsController",
    "Method": "Create",
    "RelativePath": "api/Students",
    "HttpMethod": "POST",
    "IsController": true,
    "Order": 0,
    "Parameters": [
      {
        "Name": "student",
        "Type": "sharp_01.Models.Student",
        "IsRequired": true
      }
    ],
    "ReturnTypes": []
  },
  {
    "ContainingType": "sharp_01.Controllers.TasksController",
    "Method": "GetAll",
    "RelativePath": "api/Tasks",
    "HttpMethod": "GET",
    "IsController": true,
    "Order": 0,
    "Parameters": [],
    "ReturnTypes": []
  },
  {
    "ContainingType": "sharp_01.Controllers.TasksController",
    "Method": "Create",
    "RelativePath": "api/Tasks",
    "HttpMethod": "POST",
    "IsController": true,
    "Order": 0,
    "Parameters": [
      {
        "Name": "task",
        "Type": "sharp_01.Models.TaskItem",
        "IsRequired": true
      }
    ],
    "ReturnTypes": []
  },
  {
    "ContainingType": "sharp_01.Controllers.StandController",
    "Method": "CreateEdit",
    "RelativePath": "CreateEdit",
    "HttpMethod": "POST",
    "IsController": true,
    "Order": 0,
    "Parameters": [
      {
        "Name": "StandVal",
        "Type": "sharp_01.Models.StandCars",
        "IsRequired": true
      }
    ],
    "ReturnTypes": []
  },
  {
    "ContainingType": "sharp_01.Controllers.StandController",
    "Method": "Delete",
    "RelativePath": "Delete",
    "HttpMethod": "DELETE",
    "IsController": true,
    "Order": 0,
    "Parameters": [
      {
        "Name": "CarID",
        "Type": "System.Int32",
        "IsRequired": false
      }
    ],
    "ReturnTypes": []
  },
  {
    "ContainingType": "sharp_01.Controllers.StandController",
    "Method": "GetAll",
    "RelativePath": "GetAll",
    "HttpMethod": "GET",
    "IsController": true,
    "Order": 0,
    "Parameters": [],
    "ReturnTypes": []
  }
]